LICENSE
MANIFEST.in
README.md
setup.py
django_event_procedures.egg-info/PKG-INFO
django_event_procedures.egg-info/SOURCES.txt
django_event_procedures.egg-info/dependency_links.txt
django_event_procedures.egg-info/requires.txt
django_event_procedures.egg-info/top_level.txt
event_procedures/__init__.py
event_procedures/__init__.pyc
event_procedures/admin.py
event_procedures/middleware.py
event_procedures/models.py
event_procedures/models.pyc
event_procedures/utils.py
event_procedures/migrations/0001_initial.py
event_procedures/migrations/0002_auto__add_field_action_parent.py
event_procedures/migrations/0003_auto__add_closure__add_email__add_field_action_closure.py
event_procedures/migrations/0004_auto__del_closure__del_email__del_field_action_closure__add_field_acti.py
event_procedures/migrations/0005_auto__add_email.py
event_procedures/migrations/0006_auto__add_field_email_cc__add_field_email_bcc.py
event_procedures/migrations/0007_auto__add_field_email_subject__add_field_email_message_html__add_field.py
event_procedures/migrations/0008_auto__add_field_action_name__chg_field_email_cc__chg_field_email_bcc__.py
event_procedures/migrations/0009_auto__add_closure__del_field_action_object_id__del_field_action_conten.py
event_procedures/migrations/0010_auto__chg_field_email_message_body__chg_field_email_message_html.py
event_procedures/migrations/__init__.py
event_procedures/templates/email/body/sample.html
event_procedures/templates/email/html/sample.html